pyclassifiers/__init__.py
pyclassifiers/static.py
pyclassifiers/values.py
pyclassifiers-0.0.23.dist-info/METADATA
pyclassifiers-0.0.23.dist-info/WHEEL
pyclassifiers-0.0.23.dist-info/licenses/LICENSE
pyclassifiers-0.0.23.dist-info/RECORD
