Metadata-Version: 2.4
Name: pyclassifiers
Version: 0.0.23
Summary: classifiers from pypi
Project-URL: Homepage, https://github.com/veltzer/pyclassifiers
Project-URL: Bug Tracker, https://github.com/veltzer/pyclassifiers/issues
Project-URL: Documentation, https://veltzer.github.io/pyclassifiers
Project-URL: Download, https://pypi.org/project/pyclassifiers/
Project-URL: Repository, https://github.com/veltzer/pyclassifiers
Author-email: Mark Veltzer <mark.veltzer@gmail.com>
Maintainer-email: Mark Veltzer <mark.veltzer@gmail.com>
License-Expression: MIT
License-File: LICENSE
Keywords: classifiers,distutils,pypi,python,setuptools
Classifier: Development Status :: 4 - Beta
Classifier: Environment :: Console
Classifier: License :: OSI Approved :: MIT License
Classifier: Operating System :: OS Independent
Classifier: Programming Language :: Python
Classifier: Programming Language :: Python :: 3
Classifier: Programming Language :: Python :: 3 :: Only
Classifier: Programming Language :: Python :: 3.12
Classifier: Topic :: Utilities
Requires-Python: >=3.12
Requires-Dist: requests
